meu_pacote/__init__.py
meu_pacote/main.py
meu_pacote/model.py
meu_pacote/view.py
Projeto_Banco-0.1.0.dist-info/LICENSE
Projeto_Banco-0.1.0.dist-info/METADATA
Projeto_Banco-0.1.0.dist-info/WHEEL
Projeto_Banco-0.1.0.dist-info/top_level.txt
Projeto_Banco-0.1.0.dist-info/RECORD
