Metadata-Version: 2.1
Name: Projeto_Banco
Version: 0.1.0
Summary: pacote python de um projeto POO de Bancos
Home-page: https://github.com/Hidan404/Dio---desafio-1.git
Author: Ronald
Author-email: ronaldkurouzo@gmail.com
Classifier: Programming Language :: Python :: 3
Classifier: License :: OSI Approved :: MIT License
Classifier: Operating System :: OS Independent
Requires-Python: >=3.6
License-File: LICENSE
